[
  {
    "title": "StreamRadar Netflix Placeholder",
    "year": 2026,
    "type": "movie",
    "platform": "netflix",
    "release_date": "2026-05-15",
    "overview": "Begins streaming placeholder when Google News returns no rows for this run.",
    "genres": [
      "Drama"
    ],
    "poster_image_url": null,
    "backdrop_image_url": null,
    "rating": null,
    "trailer_url": null,
    "source_url": "https://www.netflix.com/title/80057281",
    "scraped_at": "2026-06-02T09:21:30+00:00",
    "source_name": "Netflix",
    "source_domain": "netflix.com",
    "article_url": "https://www.netflix.com/title/80057281",
    "content_type": "platform_release",
    "published_at": "2026-05-15T00:00:00Z",
    "updated_at": "2026-06-02T09:21:30Z"
  }
]
